MANIFEST.in
setup.py
Yak.egg-info/PKG-INFO
Yak.egg-info/SOURCES.txt
Yak.egg-info/dependency_links.txt
Yak.egg-info/requires.txt
Yak.egg-info/top_level.txt
bin/yak
yak/__init__.py
yak/reader.py
yak/writer.py
yak/data/2012-07-20-yak.md
yak/data/archive.html
yak/data/atom.xml
yak/data/base.html
yak/data/config.py
yak/data/favicon.ico
yak/data/index.html
yak/data/post.html
yak/data/style.css
yak/web/__init__.py
yak/web/hg.py
yak/web/utils.py
yak/web/views.py
yak/web/static/style.css
yak/web/templates/base.html
yak/web/templates/dashboard.html
yak/web/templates/edit_post.html
yak/web/templates/init.html
yak/web/templates/media.html
yak/web/templates/new_post.html
yak/web/templates/posts.html
yak/web/templates/settings.html