Metadata-Version: 1.0
Name: Yak
Version: 0.2
Summary: A static blogging platform.
Home-page: http://github.com/limeburst/yak
Author: Jihyeok Seo
Author-email: me@limeburst.net
License: UNKNOWN
Platform: UNKNOWN
